slidesmith/__init__.py
slidesmith/__main__.py
slidesmith/cli.py
slidesmith/component_docs.py
slidesmith/components.py
slidesmith/config.py
slidesmith/markdown_spec.md
slidesmith/models.py
slidesmith/package.json
slidesmith/parser.py
slidesmith/renderer.py
slidesmith/server.py
slidesmith/setup.py
slidesmith/templates.py
slidesmith/themes.py
slidesmith/utils.py
slidesmith/scripts/build-simple.js
slidesmith/scripts/build.js
slidesmith/scripts/lint.js
slidesmith/scripts/lint.py
slidesmith/scripts/pdf_export.js
slidesmith/scripts/pdf_export.py
slidesmith/scripts/snapshot.js
slidesmith/scripts/snapshot.py
slidesmith/styles/base.css
slidesmith/templates/markov-pro/manifest.json
slidesmith/templates/markov-pro/tokens.json
slidesmith/templates/markov-pro/assets/icons/icon-map.json
slidesmith/templates/markov-pro/assets/icons/svg-paths.json
slidesmith/templates/markov-pro/components/index.js
slidesmith/templates/markov-pro/examples/next-steps.md
slidesmith/templates/markov-pro/examples/roi-analysis.md
slidesmith/tools/__init__.py
slidesmith/tools/__init___new.py
slidesmith/tools/build.py
slidesmith/tools/component_discovery.py
slidesmith/tools/deck_management.py
slidesmith/tools/dynamic_content.py
slidesmith/tools/export.py
slidesmith/tools/presentation.py
slidesmith/tools/quality.py
slidesmith/tools/slide_management.py
slidesmith/tools/template_config.py
slidesmith/tools/theming.py
slidesmith/tools/utilities.py
slidesmith/vendor/all.css
slidesmith/vendor/manifest.json
slidesmith/vendor/css/fira-code.css
slidesmith/vendor/css/font-awesome.min.css
slidesmith/vendor/css/inter.css
slidesmith/vendor/js/chart.min.js
slidesmith/vendor/js/tailwind.min.js
slidesmith-0.4.9.dist-info/METADATA
slidesmith-0.4.9.dist-info/WHEEL
slidesmith-0.4.9.dist-info/entry_points.txt
slidesmith-0.4.9.dist-info/licenses/LICENSE
slidesmith-0.4.9.dist-info/RECORD
