Metadata-Version: 2.4
Name: slidesmith
Version: 0.4.9
Summary: An on-device MCP server that converts Markdown to pixel-perfect slide decks
Project-URL: Homepage, https://github.com/markov/slidesmith
Project-URL: Documentation, https://slidesmith.readthedocs.io
Project-URL: Repository, https://github.com/markov/slidesmith.git
Project-URL: Issues, https://github.com/markov/slidesmith/issues
Author-email: Slidesmith Team <slidesmith@example.com>
License: MIT
License-File: LICENSE
Keywords: markdown,mcp,presentation,react,slides,tailwind
Classifier: Development Status :: 3 - Alpha
Classifier: Intended Audience :: Developers
Classifier: License :: OSI Approved :: MIT License
Classifier: Programming Language :: Python :: 3
Classifier: Programming Language :: Python :: 3.11
Classifier: Programming Language :: Python :: 3.12
Classifier: Topic :: Office/Business :: Office Suites
Classifier: Topic :: Text Processing :: Markup
Requires-Python: >=3.11
Requires-Dist: click<9.0.0,>=8.0.0
Requires-Dist: fastmcp<3.0.0,>=2.9.2
Requires-Dist: jinja2<4.0.0,>=3.0.0
Requires-Dist: jsonpatch<2.0.0,>=1.33
Requires-Dist: markdown<4.0.0,>=3.0.0
Requires-Dist: playwright<2.0.0,>=1.44.0
Requires-Dist: pydantic<3.0.0,>=2.0.0
Requires-Dist: pypdf2<4.0.0,>=3.0.0
Requires-Dist: python-dotenv<2.0.0,>=1.0.0
Requires-Dist: pyyaml<7.0.0,>=6.0.0
Requires-Dist: rich<15.0.0,>=14.0.0
Provides-Extra: dev
Requires-Dist: mypy<2.0.0,>=1.10.0; extra == 'dev'
Requires-Dist: openai<2.0.0,>=1.0.0; extra == 'dev'
Requires-Dist: pytest-asyncio<1.0.0,>=0.23.0; extra == 'dev'
Requires-Dist: pytest-cov<6.0.0,>=5.0.0; extra == 'dev'
Requires-Dist: pytest<9.0.0,>=8.0.0; extra == 'dev'
Requires-Dist: ruff<1.0.0,>=0.5.0; extra == 'dev'
